abml_cli/.python-version
abml_cli/__init__.py
abml_cli/abml_filters.py
abml_cli/abml_grids.py
abml_cli/abml_parser.py
abml_cli/abml_run.py
abml_cli/abml_yamler.py
abml_cli-0.1.19.dist-info/entry_points.txt
abml_cli-0.1.19.dist-info/METADATA
abml_cli-0.1.19.dist-info/WHEEL
abml_cli-0.1.19.dist-info/RECORD
