Metadata-Version: 2.1
Name: abml-cli
Version: 0.1.19
Summary: 
Author: DavidNaizheZhou
Author-email: 70525024+DavidNaizheZhou@users.noreply.github.com
Requires-Python: >=3.11,<4.0
Classifier: Programming Language :: Python :: 3
Classifier: Programming Language :: Python :: 3.11
Requires-Dist: click (>=8.1.3,<9.0.0)
Requires-Dist: invoke (>=2.0.0,<3.0.0)
Requires-Dist: jinja2 (>=3.1.2,<4.0.0)
Requires-Dist: numpy (>=1.24.2,<2.0.0)
Requires-Dist: pandas (>=2.0.2,<3.0.0)
Requires-Dist: pyyaml (>=6.0,<7.0)
Requires-Dist: pyyaml-include (>=1.3,<2.0)
Requires-Dist: rich (>=13.3.3,<14.0.0)
